web_search/__init__.py
web_search/arxiv.py
web_search/base.py
web_search/config.py
web_search/google.py
web_search/search.py
web_search/wikipedia.py
async_web_search-0.2.1.dist-info/METADATA
async_web_search-0.2.1.dist-info/WHEEL
async_web_search-0.2.1.dist-info/licenses/LICENSE
async_web_search-0.2.1.dist-info/RECORD
