Metadata-Version: 2.3
Name: async-web-search
Version: 0.2.1
Summary: Async web search library supporting Google, Wikipedia, and arXiv
Project-URL: Homepage, https://github.com/nwaughachukwuma/async-web-search
Project-URL: Bug Tracker, https://github.com/nwaughachukwuma/async-web-search/issues
Author: Chukwuma
License: MIT
Classifier: License :: OSI Approved :: MIT License
Classifier: Operating System :: OS Independent
Classifier: Programming Language :: Python :: 3
Classifier: Topic :: Internet :: WWW/HTTP :: Dynamic Content
Classifier: Topic :: Software Development :: Libraries :: Python Modules
Requires-Python: >=3.9
Requires-Dist: beautifulsoup4
Requires-Dist: httpx
Requires-Dist: lxml
Requires-Dist: wikipedia
